scinote_client/__init__.py
scinote_client/client/__init__.py
scinote_client/client/api/__init__.py
scinote_client/client/api/inventory_cell_client.py
scinote_client/client/api/inventory_client.py
scinote_client/client/api/inventory_column_client.py
scinote_client/client/api/inventory_column_list_item_client.py
scinote_client/client/api/inventory_item_child_client.py
scinote_client/client/api/inventory_item_client.py
scinote_client/client/api/inventory_item_parent_client.py
scinote_client/client/api/teams_client.py
scinote_client/client/models/__init__.py
scinote_client/client/models/inventories.py
scinote_client/client/models/inventory_cell.py
scinote_client/client/models/inventory_child.py
scinote_client/client/models/inventory_column_list_item.py
scinote_client/client/models/inventory_columns.py
scinote_client/client/models/inventory_item.py
scinote_client/client/models/inventory_parent.py
scinote_client/client/models/teams.py
scinote_client/orm/cell.py
scinote_client/orm/inventories.py
scinote_client/orm/inventory.py
scinote_client/orm/items.py
scinote_client-0.9.0.dist-info/licenses/LICENSE
scinote_client-0.9.0.dist-info/METADATA
scinote_client-0.9.0.dist-info/WHEEL
scinote_client-0.9.0.dist-info/top_level.txt
scinote_client-0.9.0.dist-info/RECORD
