Metadata-Version: 2.4
Name: scinote_client
Version: 0.9.0
Summary: A client for the scinote API
Author: The Sequins Software Team
License: 
Project-URL: Homepage, https://sequins.bio
Classifier: Development Status :: 3 - Alpha
Classifier: Programming Language :: Python
Requires-Python: >=3.13
License-File: LICENSE
Requires-Dist: aiocache<1.0.0,>=0.12.3
Requires-Dist: cachetools<7.0.0,>=5.5.2
Requires-Dist: httpx<1.0.0,>=0.28.1
Requires-Dist: pydantic<3.0.0,>=2.11.1
Provides-Extra: test
Requires-Dist: pytest; extra == "test"
Requires-Dist: pytest-asyncio; extra == "test"
Requires-Dist: pytest-cov; extra == "test"
Requires-Dist: pytest-env; extra == "test"
Requires-Dist: respx; extra == "test"
Dynamic: license-file
